recursivist/__init__.py
recursivist/__main__.py
recursivist/cli.py
recursivist/compare.py
recursivist/core.py
recursivist/exports.py
recursivist/jsx_export.py
recursivist-1.4.3.dist-info/METADATA
recursivist-1.4.3.dist-info/WHEEL
recursivist-1.4.3.dist-info/entry_points.txt
recursivist-1.4.3.dist-info/licenses/LICENSE
recursivist-1.4.3.dist-info/RECORD
